{
  "parameters": [
    {
      "name": "data-tchmi-name",
      "displayName": "Name",
      "allowSymbolExpressionsInObject": false,
      "visible": true,
      "type": "tchmi:general#/definitions/String",
      "category": "",
      "description": "",
      "defaultValue": "default",
      "defaultValueInternal": "default",
      "requiredOnCompile": false,
      "readOnly": false,
      "bindable": true,
      "heritable": true,
      "propertyName": "Name",
      "propertySetterName": "setName",
      "propertyGetterName": "getName",
      "refTo": ""
    },
    {
      "name": "data-tchmi-actpos",
      "displayName": "ActPos",
      "allowSymbolExpressionsInObject": false,
      "visible": true,
      "type": "tchmi:general#/definitions/LREAL",
      "category": "",
      "description": "",
      "requiredOnCompile": false,
      "readOnly": false,
      "bindable": true,
      "heritable": true,
      "propertyName": "ActPos",
      "propertySetterName": "setActPos",
      "propertyGetterName": "getActPos",
      "refTo": ""
    },
    {
      "name": "data-tchmi-setpos",
      "displayName": "SetPos",
      "allowSymbolExpressionsInObject": false,
      "visible": true,
      "type": "tchmi:general#/definitions/LREAL",
      "category": "",
      "description": "",
      "requiredOnCompile": false,
      "readOnly": false,
      "bindable": true,
      "heritable": true,
      "propertyName": "SetPos",
      "propertySetterName": "setSetPos",
      "propertyGetterName": "getSetPos",
      "refTo": ""
    },
    {
      "name": "data-tchmi-moving",
      "displayName": "Moving",
      "allowSymbolExpressionsInObject": false,
      "visible": true,
      "type": "tchmi:general#/definitions/BOOL",
      "category": "",
      "description": "",
      "requiredOnCompile": false,
      "readOnly": false,
      "bindable": true,
      "heritable": true,
      "propertyName": "Moving",
      "propertySetterName": "setMoving",
      "propertyGetterName": "getMoving",
      "refTo": ""
    },
    {
      "name": "data-tchmi-move",
      "displayName": "Move",
      "allowSymbolExpressionsInObject": false,
      "visible": true,
      "type": "tchmi:general#/definitions/BOOL",
      "category": "",
      "description": "",
      "requiredOnCompile": false,
      "readOnly": false,
      "bindable": true,
      "heritable": true,
      "propertyName": "Move",
      "propertySetterName": "setMove",
      "propertyGetterName": "getMove",
      "refTo": ""
    },
    {
      "name": "data-tchmi-enabled",
      "displayName": "Enabled",
      "allowSymbolExpressionsInObject": false,
      "visible": true,
      "type": "tchmi:general#/definitions/BOOL",
      "category": "",
      "description": "",
      "requiredOnCompile": false,
      "readOnly": false,
      "bindable": true,
      "heritable": true,
      "propertyName": "Enabled",
      "propertySetterName": "setEnabled",
      "propertyGetterName": "getEnabled",
      "refTo": ""
    }
  ],
  "virtualRights": [],
  "$schema": "./../../Packages/Beckhoff.TwinCAT.HMI.Framework.12.760.42/runtimes/native1.12-tchmi/Schema/UserControlConfig.Schema.json",
  "description": ""
}